LICENSE
MANIFEST.in
README.md
pelican_edit_url.py
setup.py
pelican_edit_url.egg-info/PKG-INFO
pelican_edit_url.egg-info/SOURCES.txt
pelican_edit_url.egg-info/dependency_links.txt
pelican_edit_url.egg-info/requires.txt
pelican_edit_url.egg-info/top_level.txt