Metadata-Version: 1.1
Name: pelican-edit-url
Version: 0.1.1
Summary: Add edit URLs to content objects.
Home-page: https://github.com/pmclanahan/pelican-edit-url
Author: Paul McLanahan
Author-email: paul@mclanahan.net
License: MIT
Platform: UNKNOWN
Classifier: Development Status :: 4 - Beta
Classifier: Environment :: Console
Classifier: Intended Audience :: Developers
Classifier: License :: OSI Approved :: MIT License
Classifier: Natural Language :: English
Classifier: Operating System :: OS Independent
Classifier: Programming Language :: Python
Classifier: Programming Language :: Python :: 2.6
Classifier: Programming Language :: Python :: 2.7
Classifier: Topic :: Internet :: WWW/HTTP
Classifier: Topic :: Software Development :: Libraries :: Python Modules
